abpandas/__init__.py
abpandas/agent.py
abpandas/model.py
abpandas/space.py
abpandas-0.0.34.dist-info/METADATA
abpandas-0.0.34.dist-info/WHEEL
abpandas-0.0.34.dist-info/top_level.txt
abpandas-0.0.34.dist-info/RECORD
