Metadata-Version: 2.1
Name: abpandas
Version: 0.0.34
Summary: Agent Based Pandas tool (ABPandas)
Author: Yahya Gamal
Author-email: <abpandas.yg@outlook.com>
Keywords: python,Agent Based Model,Spatial,Pandas
Classifier: Development Status :: 3 - Alpha
Classifier: Intended Audience :: Science/Research
Classifier: Programming Language :: Python :: 2
Classifier: Programming Language :: Python :: 3
Classifier: Operating System :: MacOS :: MacOS X
Classifier: Operating System :: Microsoft :: Windows
Requires-Dist: geopandas
Requires-Dist: pandas
Requires-Dist: fiona
Requires-Dist: pyshp
Requires-Dist: shapely
